pylogrust-0.2.0.dist-info/METADATA
pylogrust-0.2.0.dist-info/WHEEL
pylogrust/__init__.py
pylogrust/__pycache__/__init__.cpython-313.pyc
pylogrust/_pylogrust_core.cpython-313-x86_64-linux-gnu.so
pylogrust-0.2.0.dist-info/RECORD
