Metadata-Version: 2.4
Name: pylogrust
Version: 0.2.0
Summary: A high-performance Python logging library written in Rust
Author-email: KennyTANG <kennytangpublic@gmail.com>
License: MIT
Requires-Python: >=3.8
